BoxTurtle.py
BoxTurtle-1.1.6.dist-info/LICENSE
BoxTurtle-1.1.6.dist-info/METADATA
BoxTurtle-1.1.6.dist-info/WHEEL
BoxTurtle-1.1.6.dist-info/top_level.txt
BoxTurtle-1.1.6.dist-info/RECORD
