Metadata-Version: 2.1
Name: BoxTurtle
Version: 1.1.6
Summary: Simple turtle graphics library with 3D integration
Author-email: chadwickjr <chadmillimanjr@gmail.com>
License: Copyright © 2023 Chadwick Milliman
Keywords: turtle,3D,graphics
Requires-Python: >=3.10
License-File: LICENSE
